odoo/addons/shopinvader_delivery_instruction/README.rst
odoo/addons/shopinvader_delivery_instruction/__init__.py
odoo/addons/shopinvader_delivery_instruction/__manifest__.py
odoo/addons/shopinvader_delivery_instruction/i18n/shopinvader_delivery_instruction.pot
odoo/addons/shopinvader_delivery_instruction/readme/CONTRIBUTORS.rst
odoo/addons/shopinvader_delivery_instruction/readme/CREDITS.rst
odoo/addons/shopinvader_delivery_instruction/readme/DESCRIPTION.rst
odoo/addons/shopinvader_delivery_instruction/services/__init__.py
odoo/addons/shopinvader_delivery_instruction/services/abstract_sale.py
odoo/addons/shopinvader_delivery_instruction/services/cart.py
odoo/addons/shopinvader_delivery_instruction/static/description/index.html
odoo/addons/shopinvader_delivery_instruction/tests/__init__.py
odoo/addons/shopinvader_delivery_instruction/tests/test_sale_order_picking_note.py
odoo14_addon_shopinvader_delivery_instruction-14.0.1.0.2.dist-info/METADATA
odoo14_addon_shopinvader_delivery_instruction-14.0.1.0.2.dist-info/WHEEL
odoo14_addon_shopinvader_delivery_instruction-14.0.1.0.2.dist-info/top_level.txt
odoo14_addon_shopinvader_delivery_instruction-14.0.1.0.2.dist-info/RECORD
